trips/__init__.py
trips/__version__.py
trips/cli.py
trips/oslo.py
trips-0.1.2.dist-info/DESCRIPTION.rst
trips-0.1.2.dist-info/METADATA
trips-0.1.2.dist-info/RECORD
trips-0.1.2.dist-info/WHEEL
trips-0.1.2.dist-info/entry_points.txt
trips-0.1.2.dist-info/metadata.json
trips-0.1.2.dist-info/top_level.txt
