Metadata-Version: 2.0
Name: trips
Version: 0.1.2
Summary: CLI for Ruter's public transporation in Oslo
Home-page: https://github.com/staticaland/trips
Author: Anders K. Pettersen
Author-email: andstatical@gmail.com
License: MIT
Platform: UNKNOWN
Classifier: License :: OSI Approved :: MIT License
Classifier: Programming Language :: Python
Classifier: Programming Language :: Python :: 2.6
Classifier: Programming Language :: Python :: 2.7
Classifier: Programming Language :: Python :: 3
Classifier: Programming Language :: Python :: 3.3
Classifier: Programming Language :: Python :: 3.4
Classifier: Programming Language :: Python :: 3.5
Classifier: Programming Language :: Python :: 3.6
Classifier: Programming Language :: Python :: Implementation :: CPython
Classifier: Programming Language :: Python :: Implementation :: PyPy
Requires-Dist: requests
Requires-Dist: crayons
Requires-Dist: click
Requires-Dist: python-box
Requires-Dist: udatetime
